[
  {
    "id": "IMG_8851",
    "source_file": "IMG_8851.jpeg",
    "category": "layouts/master",
    "priority": "master",
    "description": "Original Kanal-Banner / CI-Referenz mit Inklusion+Humor, Follow-Element und Figur von hinten",
    "width": 1168,
    "height": 2048,
    "sha1": "208ac9f87631",
    "usage": "reference_only",
    "face_visibility": "not_primary_or_not_visible",
    "notes": "Original Nutzerreferenz. Für Prompting/CI/Asset-Matching verwenden; nicht ungeprüft öffentlich posten.",
    "path": "assets/references/layouts/master/IMG_8851.jpeg"
  },
  {
    "id": "40ee7cb9-27a9-4485-adf6-e6191d137065",
    "source_file": "40ee7cb9-27a9-4485-adf6-e6191d137065.png",
    "category": "layouts/ci_inspiration",
    "priority": "master",
    "description": "Vom Nutzer bereitgestellte Carousel-Layout-Erinnerung: Neon-Flächen, Bottom-Bar, Follow-CTA, Sticker, Slide-Zähler",
    "width": 1402,
    "height": 1122,
    "sha1": "637815ed9b4b",
    "usage": "reference_only",
    "face_visibility": "not_primary_or_not_visible",
    "notes": "Original Nutzerreferenz. Für Prompting/CI/Asset-Matching verwenden; nicht ungeprüft öffentlich posten.",
    "path": "assets/references/layouts/ci_inspiration/40ee7cb9-27a9-4485-adf6-e6191d137065.png"
  },
  {
    "id": "IMG_8875",
    "source_file": "IMG_8875.jpeg",
    "category": "character/body_silhouette",
    "priority": "master",
    "description": "Körperbau/Outfit frontal: schwarzes Polo, schwarze Shorts, schwarze Strumpfhose, Orthese links, weiße Orthesenschuhe",
    "width": 733,
    "height": 1453,
    "sha1": "945b05feeec3",
    "usage": "reference_only",
    "face_visibility": "not_primary_or_not_visible",
    "notes": "Original Nutzerreferenz. Für Prompting/CI/Asset-Matching verwenden; nicht ungeprüft öffentlich posten.",
    "path": "assets/references/character/body_silhouette/IMG_8875.jpeg"
  },
  {
    "id": "IMG_8875",
    "source_file": "IMG_8875.jpeg",
    "category": "outfits/black_polo_black_shorts",
    "priority": "master",
    "description": "Körperbau/Outfit frontal: schwarzes Polo, schwarze Shorts, schwarze Strumpfhose, Orthese links, weiße Orthesenschuhe",
    "width": 733,
    "height": 1453,
    "sha1": "945b05feeec3",
    "usage": "reference_only",
    "face_visibility": "not_primary_or_not_visible",
    "notes": "Original Nutzerreferenz. Für Prompting/CI/Asset-Matching verwenden; nicht ungeprüft öffentlich posten.",
    "path": "assets/references/outfits/black_polo_black_shorts/IMG_8875.jpeg"
  },
  {
    "id": "IMG_8875",
    "source_file": "IMG_8875.jpeg",
    "category": "orthosis/front",
    "priority": "master",
    "description": "Körperbau/Outfit frontal: schwarzes Polo, schwarze Shorts, schwarze Strumpfhose, Orthese links, weiße Orthesenschuhe",
    "width": 733,
    "height": 1453,
    "sha1": "945b05feeec3",
    "usage": "reference_only",
    "face_visibility": "not_primary_or_not_visible",
    "notes": "Original Nutzerreferenz. Für Prompting/CI/Asset-Matching verwenden; nicht ungeprüft öffentlich posten.",
    "path": "assets/references/orthosis/front/IMG_8875.jpeg"
  },
  {
    "id": "IMG_8875",
    "source_file": "IMG_8875.jpeg",
    "category": "orthopedic_shoes/sneakers",
    "priority": "master",
    "description": "Körperbau/Outfit frontal: schwarzes Polo, schwarze Shorts, schwarze Strumpfhose, Orthese links, weiße Orthesenschuhe",
    "width": 733,
    "height": 1453,
    "sha1": "945b05feeec3",
    "usage": "reference_only",
    "face_visibility": "not_primary_or_not_visible",
    "notes": "Original Nutzerreferenz. Für Prompting/CI/Asset-Matching verwenden; nicht ungeprüft öffentlich posten.",
    "path": "assets/references/orthopedic_shoes/sneakers/IMG_8875.jpeg"
  },
  {
    "id": "IMG_8875",
    "source_file": "IMG_8875.jpeg",
    "category": "locations/home_office",
    "priority": "master",
    "description": "Körperbau/Outfit frontal: schwarzes Polo, schwarze Shorts, schwarze Strumpfhose, Orthese links, weiße Orthesenschuhe",
    "width": 733,
    "height": 1453,
    "sha1": "945b05feeec3",
    "usage": "reference_only",
    "face_visibility": "not_primary_or_not_visible",
    "notes": "Original Nutzerreferenz. Für Prompting/CI/Asset-Matching verwenden; nicht ungeprüft öffentlich posten.",
    "path": "assets/references/locations/home_office/IMG_8875.jpeg"
  },
  {
    "id": "IMG_8877",
    "source_file": "IMG_8877.jpeg",
    "category": "character/body_silhouette",
    "priority": "master",
    "description": "Ganzkörper frontal, Hände hinter Rücken, gute Silhouette und Outfit-Proportionen",
    "width": 535,
    "height": 1449,
    "sha1": "68558f94f154",
    "usage": "reference_only",
    "face_visibility": "not_primary_or_not_visible",
    "notes": "Original Nutzerreferenz. Für Prompting/CI/Asset-Matching verwenden; nicht ungeprüft öffentlich posten.",
    "path": "assets/references/character/body_silhouette/IMG_8877.jpeg"
  },
  {
    "id": "IMG_8877",
    "source_file": "IMG_8877.jpeg",
    "category": "outfits/black_polo_black_shorts",
    "priority": "master",
    "description": "Ganzkörper frontal, Hände hinter Rücken, gute Silhouette und Outfit-Proportionen",
    "width": 535,
    "height": 1449,
    "sha1": "68558f94f154",
    "usage": "reference_only",
    "face_visibility": "not_primary_or_not_visible",
    "notes": "Original Nutzerreferenz. Für Prompting/CI/Asset-Matching verwenden; nicht ungeprüft öffentlich posten.",
    "path": "assets/references/outfits/black_polo_black_shorts/IMG_8877.jpeg"
  },
  {
    "id": "IMG_8877",
    "source_file": "IMG_8877.jpeg",
    "category": "orthosis/front",
    "priority": "master",
    "description": "Ganzkörper frontal, Hände hinter Rücken, gute Silhouette und Outfit-Proportionen",
    "width": 535,
    "height": 1449,
    "sha1": "68558f94f154",
    "usage": "reference_only",
    "face_visibility": "not_primary_or_not_visible",
    "notes": "Original Nutzerreferenz. Für Prompting/CI/Asset-Matching verwenden; nicht ungeprüft öffentlich posten.",
    "path": "assets/references/orthosis/front/IMG_8877.jpeg"
  },
  {
    "id": "IMG_8877",
    "source_file": "IMG_8877.jpeg",
    "category": "orthopedic_shoes/sneakers",
    "priority": "master",
    "description": "Ganzkörper frontal, Hände hinter Rücken, gute Silhouette und Outfit-Proportionen",
    "width": 535,
    "height": 1449,
    "sha1": "68558f94f154",
    "usage": "reference_only",
    "face_visibility": "not_primary_or_not_visible",
    "notes": "Original Nutzerreferenz. Für Prompting/CI/Asset-Matching verwenden; nicht ungeprüft öffentlich posten.",
    "path": "assets/references/orthopedic_shoes/sneakers/IMG_8877.jpeg"
  },
  {
    "id": "IMG_8877",
    "source_file": "IMG_8877.jpeg",
    "category": "locations/home_office",
    "priority": "master",
    "description": "Ganzkörper frontal, Hände hinter Rücken, gute Silhouette und Outfit-Proportionen",
    "width": 535,
    "height": 1449,
    "sha1": "68558f94f154",
    "usage": "reference_only",
    "face_visibility": "not_primary_or_not_visible",
    "notes": "Original Nutzerreferenz. Für Prompting/CI/Asset-Matching verwenden; nicht ungeprüft öffentlich posten.",
    "path": "assets/references/locations/home_office/IMG_8877.jpeg"
  },
  {
    "id": "IMG_8876",
    "source_file": "IMG_8876.jpeg",
    "category": "character/body_silhouette",
    "priority": "approved",
    "description": "Ganzkörper frontal, sichtbare Orthese und Schuhe, Outfit-Referenz",
    "width": 823,
    "height": 1446,
    "sha1": "c89631e6b35c",
    "usage": "reference_only",
    "face_visibility": "not_primary_or_not_visible",
    "notes": "Original Nutzerreferenz. Für Prompting/CI/Asset-Matching verwenden; nicht ungeprüft öffentlich posten.",
    "path": "assets/references/character/body_silhouette/IMG_8876.jpeg"
  },
  {
    "id": "IMG_8876",
    "source_file": "IMG_8876.jpeg",
    "category": "outfits/black_polo_black_shorts",
    "priority": "approved",
    "description": "Ganzkörper frontal, sichtbare Orthese und Schuhe, Outfit-Referenz",
    "width": 823,
    "height": 1446,
    "sha1": "c89631e6b35c",
    "usage": "reference_only",
    "face_visibility": "not_primary_or_not_visible",
    "notes": "Original Nutzerreferenz. Für Prompting/CI/Asset-Matching verwenden; nicht ungeprüft öffentlich posten.",
    "path": "assets/references/outfits/black_polo_black_shorts/IMG_8876.jpeg"
  },
  {
    "id": "IMG_8876",
    "source_file": "IMG_8876.jpeg",
    "category": "orthosis/front",
    "priority": "approved",
    "description": "Ganzkörper frontal, sichtbare Orthese und Schuhe, Outfit-Referenz",
    "width": 823,
    "height": 1446,
    "sha1": "c89631e6b35c",
    "usage": "reference_only",
    "face_visibility": "not_primary_or_not_visible",
    "notes": "Original Nutzerreferenz. Für Prompting/CI/Asset-Matching verwenden; nicht ungeprüft öffentlich posten.",
    "path": "assets/references/orthosis/front/IMG_8876.jpeg"
  },
  {
    "id": "IMG_8876",
    "source_file": "IMG_8876.jpeg",
    "category": "orthopedic_shoes/sneakers",
    "priority": "approved",
    "description": "Ganzkörper frontal, sichtbare Orthese und Schuhe, Outfit-Referenz",
    "width": 823,
    "height": 1446,
    "sha1": "c89631e6b35c",
    "usage": "reference_only",
    "face_visibility": "not_primary_or_not_visible",
    "notes": "Original Nutzerreferenz. Für Prompting/CI/Asset-Matching verwenden; nicht ungeprüft öffentlich posten.",
    "path": "assets/references/orthopedic_shoes/sneakers/IMG_8876.jpeg"
  },
  {
    "id": "IMG_8876",
    "source_file": "IMG_8876.jpeg",
    "category": "locations/home_office",
    "priority": "approved",
    "description": "Ganzkörper frontal, sichtbare Orthese und Schuhe, Outfit-Referenz",
    "width": 823,
    "height": 1446,
    "sha1": "c89631e6b35c",
    "usage": "reference_only",
    "face_visibility": "not_primary_or_not_visible",
    "notes": "Original Nutzerreferenz. Für Prompting/CI/Asset-Matching verwenden; nicht ungeprüft öffentlich posten.",
    "path": "assets/references/locations/home_office/IMG_8876.jpeg"
  },
  {
    "id": "IMG_8879",
    "source_file": "IMG_8879.jpeg",
    "category": "character/body_silhouette",
    "priority": "approved",
    "description": "Körperbau/Outfit frontal, normale Figur, Poloshirt und Shorts",
    "width": 828,
    "height": 1689,
    "sha1": "369c532aedfa",
    "usage": "reference_only",
    "face_visibility": "not_primary_or_not_visible",
    "notes": "Original Nutzerreferenz. Für Prompting/CI/Asset-Matching verwenden; nicht ungeprüft öffentlich posten.",
    "path": "assets/references/character/body_silhouette/IMG_8879.jpeg"
  },
  {
    "id": "IMG_8879",
    "source_file": "IMG_8879.jpeg",
    "category": "outfits/black_polo_black_shorts",
    "priority": "approved",
    "description": "Körperbau/Outfit frontal, normale Figur, Poloshirt und Shorts",
    "width": 828,
    "height": 1689,
    "sha1": "369c532aedfa",
    "usage": "reference_only",
    "face_visibility": "not_primary_or_not_visible",
    "notes": "Original Nutzerreferenz. Für Prompting/CI/Asset-Matching verwenden; nicht ungeprüft öffentlich posten.",
    "path": "assets/references/outfits/black_polo_black_shorts/IMG_8879.jpeg"
  },
  {
    "id": "IMG_8879",
    "source_file": "IMG_8879.jpeg",
    "category": "orthosis/front",
    "priority": "approved",
    "description": "Körperbau/Outfit frontal, normale Figur, Poloshirt und Shorts",
    "width": 828,
    "height": 1689,
    "sha1": "369c532aedfa",
    "usage": "reference_only",
    "face_visibility": "not_primary_or_not_visible",
    "notes": "Original Nutzerreferenz. Für Prompting/CI/Asset-Matching verwenden; nicht ungeprüft öffentlich posten.",
    "path": "assets/references/orthosis/front/IMG_8879.jpeg"
  },
  {
    "id": "IMG_8879",
    "source_file": "IMG_8879.jpeg",
    "category": "locations/home_office",
    "priority": "approved",
    "description": "Körperbau/Outfit frontal, normale Figur, Poloshirt und Shorts",
    "width": 828,
    "height": 1689,
    "sha1": "369c532aedfa",
    "usage": "reference_only",
    "face_visibility": "not_primary_or_not_visible",
    "notes": "Original Nutzerreferenz. Für Prompting/CI/Asset-Matching verwenden; nicht ungeprüft öffentlich posten.",
    "path": "assets/references/locations/home_office/IMG_8879.jpeg"
  },
  {
    "id": "IMG_8878",
    "source_file": "IMG_8878.jpeg",
    "category": "character/body_silhouette",
    "priority": "approved",
    "description": "Seitlich/rückwärtige Outfit- und Orthesenreferenz",
    "width": 581,
    "height": 1497,
    "sha1": "7934f611d6ca",
    "usage": "reference_only",
    "face_visibility": "not_primary_or_not_visible",
    "notes": "Original Nutzerreferenz. Für Prompting/CI/Asset-Matching verwenden; nicht ungeprüft öffentlich posten.",
    "path": "assets/references/character/body_silhouette/IMG_8878.jpeg"
  },
  {
    "id": "IMG_8878",
    "source_file": "IMG_8878.jpeg",
    "category": "outfits/black_polo_black_shorts",
    "priority": "approved",
    "description": "Seitlich/rückwärtige Outfit- und Orthesenreferenz",
    "width": 581,
    "height": 1497,
    "sha1": "7934f611d6ca",
    "usage": "reference_only",
    "face_visibility": "not_primary_or_not_visible",
    "notes": "Original Nutzerreferenz. Für Prompting/CI/Asset-Matching verwenden; nicht ungeprüft öffentlich posten.",
    "path": "assets/references/outfits/black_polo_black_shorts/IMG_8878.jpeg"
  },
  {
    "id": "IMG_8878",
    "source_file": "IMG_8878.jpeg",
    "category": "orthosis/side",
    "priority": "approved",
    "description": "Seitlich/rückwärtige Outfit- und Orthesenreferenz",
    "width": 581,
    "height": 1497,
    "sha1": "7934f611d6ca",
    "usage": "reference_only",
    "face_visibility": "not_primary_or_not_visible",
    "notes": "Original Nutzerreferenz. Für Prompting/CI/Asset-Matching verwenden; nicht ungeprüft öffentlich posten.",
    "path": "assets/references/orthosis/side/IMG_8878.jpeg"
  },
  {
    "id": "IMG_8878",
    "source_file": "IMG_8878.jpeg",
    "category": "locations/home_office",
    "priority": "approved",
    "description": "Seitlich/rückwärtige Outfit- und Orthesenreferenz",
    "width": 581,
    "height": 1497,
    "sha1": "7934f611d6ca",
    "usage": "reference_only",
    "face_visibility": "not_primary_or_not_visible",
    "notes": "Original Nutzerreferenz. Für Prompting/CI/Asset-Matching verwenden; nicht ungeprüft öffentlich posten.",
    "path": "assets/references/locations/home_office/IMG_8878.jpeg"
  },
  {
    "id": "IMG_8880",
    "source_file": "IMG_8880.jpeg",
    "category": "character/body_silhouette",
    "priority": "approved",
    "description": "Leichter Schritt/Bewegung frontal, Orthese sichtbar",
    "width": 634,
    "height": 1483,
    "sha1": "36fc9b9a202a",
    "usage": "reference_only",
    "face_visibility": "not_primary_or_not_visible",
    "notes": "Original Nutzerreferenz. Für Prompting/CI/Asset-Matching verwenden; nicht ungeprüft öffentlich posten.",
    "path": "assets/references/character/body_silhouette/IMG_8880.jpeg"
  },
  {
    "id": "IMG_8880",
    "source_file": "IMG_8880.jpeg",
    "category": "outfits/black_polo_black_shorts",
    "priority": "approved",
    "description": "Leichter Schritt/Bewegung frontal, Orthese sichtbar",
    "width": 634,
    "height": 1483,
    "sha1": "36fc9b9a202a",
    "usage": "reference_only",
    "face_visibility": "not_primary_or_not_visible",
    "notes": "Original Nutzerreferenz. Für Prompting/CI/Asset-Matching verwenden; nicht ungeprüft öffentlich posten.",
    "path": "assets/references/outfits/black_polo_black_shorts/IMG_8880.jpeg"
  },
  {
    "id": "IMG_8880",
    "source_file": "IMG_8880.jpeg",
    "category": "orthosis/front",
    "priority": "approved",
    "description": "Leichter Schritt/Bewegung frontal, Orthese sichtbar",
    "width": 634,
    "height": 1483,
    "sha1": "36fc9b9a202a",
    "usage": "reference_only",
    "face_visibility": "not_primary_or_not_visible",
    "notes": "Original Nutzerreferenz. Für Prompting/CI/Asset-Matching verwenden; nicht ungeprüft öffentlich posten.",
    "path": "assets/references/orthosis/front/IMG_8880.jpeg"
  },
  {
    "id": "IMG_8880",
    "source_file": "IMG_8880.jpeg",
    "category": "orthopedic_shoes/sneakers",
    "priority": "approved",
    "description": "Leichter Schritt/Bewegung frontal, Orthese sichtbar",
    "width": 634,
    "height": 1483,
    "sha1": "36fc9b9a202a",
    "usage": "reference_only",
    "face_visibility": "not_primary_or_not_visible",
    "notes": "Original Nutzerreferenz. Für Prompting/CI/Asset-Matching verwenden; nicht ungeprüft öffentlich posten.",
    "path": "assets/references/orthopedic_shoes/sneakers/IMG_8880.jpeg"
  },
  {
    "id": "IMG_8880",
    "source_file": "IMG_8880.jpeg",
    "category": "locations/home_office",
    "priority": "approved",
    "description": "Leichter Schritt/Bewegung frontal, Orthese sichtbar",
    "width": 634,
    "height": 1483,
    "sha1": "36fc9b9a202a",
    "usage": "reference_only",
    "face_visibility": "not_primary_or_not_visible",
    "notes": "Original Nutzerreferenz. Für Prompting/CI/Asset-Matching verwenden; nicht ungeprüft öffentlich posten.",
    "path": "assets/references/locations/home_office/IMG_8880.jpeg"
  },
  {
    "id": "IMG_8881",
    "source_file": "IMG_8881.jpeg",
    "category": "character/body_silhouette",
    "priority": "approved",
    "description": "Low-angle Silhouette vor Fenster, Schuhe/Orthese",
    "width": 1053,
    "height": 1943,
    "sha1": "b07573b60747",
    "usage": "reference_only",
    "face_visibility": "not_primary_or_not_visible",
    "notes": "Original Nutzerreferenz. Für Prompting/CI/Asset-Matching verwenden; nicht ungeprüft öffentlich posten.",
    "path": "assets/references/character/body_silhouette/IMG_8881.jpeg"
  },
  {
    "id": "IMG_8881",
    "source_file": "IMG_8881.jpeg",
    "category": "orthosis/front",
    "priority": "approved",
    "description": "Low-angle Silhouette vor Fenster, Schuhe/Orthese",
    "width": 1053,
    "height": 1943,
    "sha1": "b07573b60747",
    "usage": "reference_only",
    "face_visibility": "not_primary_or_not_visible",
    "notes": "Original Nutzerreferenz. Für Prompting/CI/Asset-Matching verwenden; nicht ungeprüft öffentlich posten.",
    "path": "assets/references/orthosis/front/IMG_8881.jpeg"
  },
  {
    "id": "IMG_8881",
    "source_file": "IMG_8881.jpeg",
    "category": "orthopedic_shoes/sneakers",
    "priority": "approved",
    "description": "Low-angle Silhouette vor Fenster, Schuhe/Orthese",
    "width": 1053,
    "height": 1943,
    "sha1": "b07573b60747",
    "usage": "reference_only",
    "face_visibility": "not_primary_or_not_visible",
    "notes": "Original Nutzerreferenz. Für Prompting/CI/Asset-Matching verwenden; nicht ungeprüft öffentlich posten.",
    "path": "assets/references/orthopedic_shoes/sneakers/IMG_8881.jpeg"
  },
  {
    "id": "IMG_8881",
    "source_file": "IMG_8881.jpeg",
    "category": "locations/home_office",
    "priority": "approved",
    "description": "Low-angle Silhouette vor Fenster, Schuhe/Orthese",
    "width": 1053,
    "height": 1943,
    "sha1": "b07573b60747",
    "usage": "reference_only",
    "face_visibility": "not_primary_or_not_visible",
    "notes": "Original Nutzerreferenz. Für Prompting/CI/Asset-Matching verwenden; nicht ungeprüft öffentlich posten.",
    "path": "assets/references/locations/home_office/IMG_8881.jpeg"
  },
  {
    "id": "IMG_8882",
    "source_file": "IMG_8882.jpeg",
    "category": "character/body_silhouette",
    "priority": "approved",
    "description": "Low-angle Ganzkörper, Orthese, weiße Schuhe",
    "width": 747,
    "height": 1662,
    "sha1": "82d11c14f968",
    "usage": "reference_only",
    "face_visibility": "not_primary_or_not_visible",
    "notes": "Original Nutzerreferenz. Für Prompting/CI/Asset-Matching verwenden; nicht ungeprüft öffentlich posten.",
    "path": "assets/references/character/body_silhouette/IMG_8882.jpeg"
  },
  {
    "id": "IMG_8882",
    "source_file": "IMG_8882.jpeg",
    "category": "orthosis/front",
    "priority": "approved",
    "description": "Low-angle Ganzkörper, Orthese, weiße Schuhe",
    "width": 747,
    "height": 1662,
    "sha1": "82d11c14f968",
    "usage": "reference_only",
    "face_visibility": "not_primary_or_not_visible",
    "notes": "Original Nutzerreferenz. Für Prompting/CI/Asset-Matching verwenden; nicht ungeprüft öffentlich posten.",
    "path": "assets/references/orthosis/front/IMG_8882.jpeg"
  },
  {
    "id": "IMG_8882",
    "source_file": "IMG_8882.jpeg",
    "category": "orthopedic_shoes/sneakers",
    "priority": "approved",
    "description": "Low-angle Ganzkörper, Orthese, weiße Schuhe",
    "width": 747,
    "height": 1662,
    "sha1": "82d11c14f968",
    "usage": "reference_only",
    "face_visibility": "not_primary_or_not_visible",
    "notes": "Original Nutzerreferenz. Für Prompting/CI/Asset-Matching verwenden; nicht ungeprüft öffentlich posten.",
    "path": "assets/references/orthopedic_shoes/sneakers/IMG_8882.jpeg"
  },
  {
    "id": "IMG_8882",
    "source_file": "IMG_8882.jpeg",
    "category": "outfits/black_polo_black_shorts",
    "priority": "approved",
    "description": "Low-angle Ganzkörper, Orthese, weiße Schuhe",
    "width": 747,
    "height": 1662,
    "sha1": "82d11c14f968",
    "usage": "reference_only",
    "face_visibility": "not_primary_or_not_visible",
    "notes": "Original Nutzerreferenz. Für Prompting/CI/Asset-Matching verwenden; nicht ungeprüft öffentlich posten.",
    "path": "assets/references/outfits/black_polo_black_shorts/IMG_8882.jpeg"
  },
  {
    "id": "IMG_8884",
    "source_file": "IMG_8884.jpeg",
    "category": "character/body_silhouette",
    "priority": "approved",
    "description": "Low-angle Schrittpose, Orthese und Schuhe dominant",
    "width": 737,
    "height": 1727,
    "sha1": "083770028309",
    "usage": "reference_only",
    "face_visibility": "not_primary_or_not_visible",
    "notes": "Original Nutzerreferenz. Für Prompting/CI/Asset-Matching verwenden; nicht ungeprüft öffentlich posten.",
    "path": "assets/references/character/body_silhouette/IMG_8884.jpeg"
  },
  {
    "id": "IMG_8884",
    "source_file": "IMG_8884.jpeg",
    "category": "orthosis/front",
    "priority": "approved",
    "description": "Low-angle Schrittpose, Orthese und Schuhe dominant",
    "width": 737,
    "height": 1727,
    "sha1": "083770028309",
    "usage": "reference_only",
    "face_visibility": "not_primary_or_not_visible",
    "notes": "Original Nutzerreferenz. Für Prompting/CI/Asset-Matching verwenden; nicht ungeprüft öffentlich posten.",
    "path": "assets/references/orthosis/front/IMG_8884.jpeg"
  },
  {
    "id": "IMG_8884",
    "source_file": "IMG_8884.jpeg",
    "category": "orthopedic_shoes/sneakers",
    "priority": "approved",
    "description": "Low-angle Schrittpose, Orthese und Schuhe dominant",
    "width": 737,
    "height": 1727,
    "sha1": "083770028309",
    "usage": "reference_only",
    "face_visibility": "not_primary_or_not_visible",
    "notes": "Original Nutzerreferenz. Für Prompting/CI/Asset-Matching verwenden; nicht ungeprüft öffentlich posten.",
    "path": "assets/references/orthopedic_shoes/sneakers/IMG_8884.jpeg"
  },
  {
    "id": "IMG_8884",
    "source_file": "IMG_8884.jpeg",
    "category": "outfits/black_polo_black_shorts",
    "priority": "approved",
    "description": "Low-angle Schrittpose, Orthese und Schuhe dominant",
    "width": 737,
    "height": 1727,
    "sha1": "083770028309",
    "usage": "reference_only",
    "face_visibility": "not_primary_or_not_visible",
    "notes": "Original Nutzerreferenz. Für Prompting/CI/Asset-Matching verwenden; nicht ungeprüft öffentlich posten.",
    "path": "assets/references/outfits/black_polo_black_shorts/IMG_8884.jpeg"
  },
  {
    "id": "IMG_8885",
    "source_file": "IMG_8885.jpeg",
    "category": "orthosis/side",
    "priority": "master",
    "description": "Seitenansicht Orthese und Orthesenschuh, Details",
    "width": 566,
    "height": 1398,
    "sha1": "ca7ffea3c3b6",
    "usage": "reference_only",
    "face_visibility": "not_primary_or_not_visible",
    "notes": "Original Nutzerreferenz. Für Prompting/CI/Asset-Matching verwenden; nicht ungeprüft öffentlich posten.",
    "path": "assets/references/orthosis/side/IMG_8885.jpeg"
  },
  {
    "id": "IMG_8885",
    "source_file": "IMG_8885.jpeg",
    "category": "orthopedic_shoes/sneakers",
    "priority": "master",
    "description": "Seitenansicht Orthese und Orthesenschuh, Details",
    "width": 566,
    "height": 1398,
    "sha1": "ca7ffea3c3b6",
    "usage": "reference_only",
    "face_visibility": "not_primary_or_not_visible",
    "notes": "Original Nutzerreferenz. Für Prompting/CI/Asset-Matching verwenden; nicht ungeprüft öffentlich posten.",
    "path": "assets/references/orthopedic_shoes/sneakers/IMG_8885.jpeg"
  },
  {
    "id": "IMG_8885",
    "source_file": "IMG_8885.jpeg",
    "category": "outfits/black_polo_black_shorts",
    "priority": "master",
    "description": "Seitenansicht Orthese und Orthesenschuh, Details",
    "width": 566,
    "height": 1398,
    "sha1": "ca7ffea3c3b6",
    "usage": "reference_only",
    "face_visibility": "not_primary_or_not_visible",
    "notes": "Original Nutzerreferenz. Für Prompting/CI/Asset-Matching verwenden; nicht ungeprüft öffentlich posten.",
    "path": "assets/references/outfits/black_polo_black_shorts/IMG_8885.jpeg"
  },
  {
    "id": "IMG_8886",
    "source_file": "IMG_8886.jpeg",
    "category": "character/body_silhouette",
    "priority": "approved",
    "description": "Walking-Pose frontal, natürliche Bewegung",
    "width": 423,
    "height": 1082,
    "sha1": "23b8079570d5",
    "usage": "reference_only",
    "face_visibility": "not_primary_or_not_visible",
    "notes": "Original Nutzerreferenz. Für Prompting/CI/Asset-Matching verwenden; nicht ungeprüft öffentlich posten.",
    "path": "assets/references/character/body_silhouette/IMG_8886.jpeg"
  },
  {
    "id": "IMG_8886",
    "source_file": "IMG_8886.jpeg",
    "category": "orthosis/front",
    "priority": "approved",
    "description": "Walking-Pose frontal, natürliche Bewegung",
    "width": 423,
    "height": 1082,
    "sha1": "23b8079570d5",
    "usage": "reference_only",
    "face_visibility": "not_primary_or_not_visible",
    "notes": "Original Nutzerreferenz. Für Prompting/CI/Asset-Matching verwenden; nicht ungeprüft öffentlich posten.",
    "path": "assets/references/orthosis/front/IMG_8886.jpeg"
  },
  {
    "id": "IMG_8886",
    "source_file": "IMG_8886.jpeg",
    "category": "orthopedic_shoes/sneakers",
    "priority": "approved",
    "description": "Walking-Pose frontal, natürliche Bewegung",
    "width": 423,
    "height": 1082,
    "sha1": "23b8079570d5",
    "usage": "reference_only",
    "face_visibility": "not_primary_or_not_visible",
    "notes": "Original Nutzerreferenz. Für Prompting/CI/Asset-Matching verwenden; nicht ungeprüft öffentlich posten.",
    "path": "assets/references/orthopedic_shoes/sneakers/IMG_8886.jpeg"
  },
  {
    "id": "IMG_8886",
    "source_file": "IMG_8886.jpeg",
    "category": "outfits/black_polo_black_shorts",
    "priority": "approved",
    "description": "Walking-Pose frontal, natürliche Bewegung",
    "width": 423,
    "height": 1082,
    "sha1": "23b8079570d5",
    "usage": "reference_only",
    "face_visibility": "not_primary_or_not_visible",
    "notes": "Original Nutzerreferenz. Für Prompting/CI/Asset-Matching verwenden; nicht ungeprüft öffentlich posten.",
    "path": "assets/references/outfits/black_polo_black_shorts/IMG_8886.jpeg"
  },
  {
    "id": "IMG_8868",
    "source_file": "IMG_8868.jpeg",
    "category": "orthopedic_shoes/sneakers",
    "priority": "master",
    "description": "Zug/POV Schuhe und schwarze Strumpfhose",
    "width": 1536,
    "height": 2048,
    "sha1": "fa1636aad991",
    "usage": "reference_only",
    "face_visibility": "not_primary_or_not_visible",
    "notes": "Original Nutzerreferenz. Für Prompting/CI/Asset-Matching verwenden; nicht ungeprüft öffentlich posten.",
    "path": "assets/references/orthopedic_shoes/sneakers/IMG_8868.jpeg"
  },
  {
    "id": "IMG_8868",
    "source_file": "IMG_8868.jpeg",
    "category": "locations/train",
    "priority": "master",
    "description": "Zug/POV Schuhe und schwarze Strumpfhose",
    "width": 1536,
    "height": 2048,
    "sha1": "fa1636aad991",
    "usage": "reference_only",
    "face_visibility": "not_primary_or_not_visible",
    "notes": "Original Nutzerreferenz. Für Prompting/CI/Asset-Matching verwenden; nicht ungeprüft öffentlich posten.",
    "path": "assets/references/locations/train/IMG_8868.jpeg"
  },
  {
    "id": "IMG_8868",
    "source_file": "IMG_8868.jpeg",
    "category": "outfits/tights_black",
    "priority": "master",
    "description": "Zug/POV Schuhe und schwarze Strumpfhose",
    "width": 1536,
    "height": 2048,
    "sha1": "fa1636aad991",
    "usage": "reference_only",
    "face_visibility": "not_primary_or_not_visible",
    "notes": "Original Nutzerreferenz. Für Prompting/CI/Asset-Matching verwenden; nicht ungeprüft öffentlich posten.",
    "path": "assets/references/outfits/tights_black/IMG_8868.jpeg"
  },
  {
    "id": "IMG_8867",
    "source_file": "IMG_8867.jpeg",
    "category": "orthopedic_shoes/sneakers",
    "priority": "approved",
    "description": "Zug/POV Schuhe und schwarze Strumpfhose, Variante",
    "width": 1536,
    "height": 2048,
    "sha1": "4de1c8a149f3",
    "usage": "reference_only",
    "face_visibility": "not_primary_or_not_visible",
    "notes": "Original Nutzerreferenz. Für Prompting/CI/Asset-Matching verwenden; nicht ungeprüft öffentlich posten.",
    "path": "assets/references/orthopedic_shoes/sneakers/IMG_8867.jpeg"
  },
  {
    "id": "IMG_8867",
    "source_file": "IMG_8867.jpeg",
    "category": "locations/train",
    "priority": "approved",
    "description": "Zug/POV Schuhe und schwarze Strumpfhose, Variante",
    "width": 1536,
    "height": 2048,
    "sha1": "4de1c8a149f3",
    "usage": "reference_only",
    "face_visibility": "not_primary_or_not_visible",
    "notes": "Original Nutzerreferenz. Für Prompting/CI/Asset-Matching verwenden; nicht ungeprüft öffentlich posten.",
    "path": "assets/references/locations/train/IMG_8867.jpeg"
  },
  {
    "id": "IMG_8867",
    "source_file": "IMG_8867.jpeg",
    "category": "outfits/tights_black",
    "priority": "approved",
    "description": "Zug/POV Schuhe und schwarze Strumpfhose, Variante",
    "width": 1536,
    "height": 2048,
    "sha1": "4de1c8a149f3",
    "usage": "reference_only",
    "face_visibility": "not_primary_or_not_visible",
    "notes": "Original Nutzerreferenz. Für Prompting/CI/Asset-Matching verwenden; nicht ungeprüft öffentlich posten.",
    "path": "assets/references/outfits/tights_black/IMG_8867.jpeg"
  },
  {
    "id": "IMG_8864",
    "source_file": "IMG_8864.jpeg",
    "category": "orthosis/front",
    "priority": "master",
    "description": "Zug/POV Orthese auf linker Seite, gute Referenz für unterwegs",
    "width": 1536,
    "height": 2048,
    "sha1": "741cb44bfe84",
    "usage": "reference_only",
    "face_visibility": "not_primary_or_not_visible",
    "notes": "Original Nutzerreferenz. Für Prompting/CI/Asset-Matching verwenden; nicht ungeprüft öffentlich posten.",
    "path": "assets/references/orthosis/front/IMG_8864.jpeg"
  },
  {
    "id": "IMG_8864",
    "source_file": "IMG_8864.jpeg",
    "category": "locations/train",
    "priority": "master",
    "description": "Zug/POV Orthese auf linker Seite, gute Referenz für unterwegs",
    "width": 1536,
    "height": 2048,
    "sha1": "741cb44bfe84",
    "usage": "reference_only",
    "face_visibility": "not_primary_or_not_visible",
    "notes": "Original Nutzerreferenz. Für Prompting/CI/Asset-Matching verwenden; nicht ungeprüft öffentlich posten.",
    "path": "assets/references/locations/train/IMG_8864.jpeg"
  },
  {
    "id": "IMG_8864",
    "source_file": "IMG_8864.jpeg",
    "category": "outfits/tights_black",
    "priority": "master",
    "description": "Zug/POV Orthese auf linker Seite, gute Referenz für unterwegs",
    "width": 1536,
    "height": 2048,
    "sha1": "741cb44bfe84",
    "usage": "reference_only",
    "face_visibility": "not_primary_or_not_visible",
    "notes": "Original Nutzerreferenz. Für Prompting/CI/Asset-Matching verwenden; nicht ungeprüft öffentlich posten.",
    "path": "assets/references/outfits/tights_black/IMG_8864.jpeg"
  },
  {
    "id": "IMG_8859",
    "source_file": "IMG_8859.jpeg",
    "category": "orthosis/details",
    "priority": "master",
    "description": "Nahaufnahme Orthesen-Gelenk/Gurte im Zug",
    "width": 2048,
    "height": 1536,
    "sha1": "ba82b0ba310a",
    "usage": "reference_only",
    "face_visibility": "not_primary_or_not_visible",
    "notes": "Original Nutzerreferenz. Für Prompting/CI/Asset-Matching verwenden; nicht ungeprüft öffentlich posten.",
    "path": "assets/references/orthosis/details/IMG_8859.jpeg"
  },
  {
    "id": "IMG_8859",
    "source_file": "IMG_8859.jpeg",
    "category": "locations/train",
    "priority": "master",
    "description": "Nahaufnahme Orthesen-Gelenk/Gurte im Zug",
    "width": 2048,
    "height": 1536,
    "sha1": "ba82b0ba310a",
    "usage": "reference_only",
    "face_visibility": "not_primary_or_not_visible",
    "notes": "Original Nutzerreferenz. Für Prompting/CI/Asset-Matching verwenden; nicht ungeprüft öffentlich posten.",
    "path": "assets/references/locations/train/IMG_8859.jpeg"
  },
  {
    "id": "IMG_8860",
    "source_file": "IMG_8860.jpeg",
    "category": "orthosis/details",
    "priority": "master",
    "description": "Nahaufnahme Orthesen-Gurte/Gelenk im Zug, gedrehte Perspektive",
    "width": 2048,
    "height": 1536,
    "sha1": "230d7a819075",
    "usage": "reference_only",
    "face_visibility": "not_primary_or_not_visible",
    "notes": "Original Nutzerreferenz. Für Prompting/CI/Asset-Matching verwenden; nicht ungeprüft öffentlich posten.",
    "path": "assets/references/orthosis/details/IMG_8860.jpeg"
  },
  {
    "id": "IMG_8860",
    "source_file": "IMG_8860.jpeg",
    "category": "orthosis/side",
    "priority": "master",
    "description": "Nahaufnahme Orthesen-Gurte/Gelenk im Zug, gedrehte Perspektive",
    "width": 2048,
    "height": 1536,
    "sha1": "230d7a819075",
    "usage": "reference_only",
    "face_visibility": "not_primary_or_not_visible",
    "notes": "Original Nutzerreferenz. Für Prompting/CI/Asset-Matching verwenden; nicht ungeprüft öffentlich posten.",
    "path": "assets/references/orthosis/side/IMG_8860.jpeg"
  },
  {
    "id": "IMG_8860",
    "source_file": "IMG_8860.jpeg",
    "category": "locations/train",
    "priority": "master",
    "description": "Nahaufnahme Orthesen-Gurte/Gelenk im Zug, gedrehte Perspektive",
    "width": 2048,
    "height": 1536,
    "sha1": "230d7a819075",
    "usage": "reference_only",
    "face_visibility": "not_primary_or_not_visible",
    "notes": "Original Nutzerreferenz. Für Prompting/CI/Asset-Matching verwenden; nicht ungeprüft öffentlich posten.",
    "path": "assets/references/locations/train/IMG_8860.jpeg"
  },
  {
    "id": "IMG_8896",
    "source_file": "IMG_8896.jpeg",
    "category": "diapers/product_in_hand",
    "priority": "master",
    "description": "Inkontinenzprodukt in der Hand vor schwarzer Strumpfhose, Produktvolumen",
    "width": 1033,
    "height": 1720,
    "sha1": "b6243a72b343",
    "usage": "reference_only",
    "face_visibility": "not_primary_or_not_visible",
    "notes": "Original Nutzerreferenz. Für Prompting/CI/Asset-Matching verwenden; nicht ungeprüft öffentlich posten.",
    "path": "assets/references/diapers/product_in_hand/IMG_8896.jpeg"
  },
  {
    "id": "IMG_8896",
    "source_file": "IMG_8896.jpeg",
    "category": "diapers/details_closeup",
    "priority": "master",
    "description": "Inkontinenzprodukt in der Hand vor schwarzer Strumpfhose, Produktvolumen",
    "width": 1033,
    "height": 1720,
    "sha1": "b6243a72b343",
    "usage": "reference_only",
    "face_visibility": "not_primary_or_not_visible",
    "notes": "Original Nutzerreferenz. Für Prompting/CI/Asset-Matching verwenden; nicht ungeprüft öffentlich posten.",
    "path": "assets/references/diapers/details_closeup/IMG_8896.jpeg"
  },
  {
    "id": "IMG_8896",
    "source_file": "IMG_8896.jpeg",
    "category": "outfits/tights_black",
    "priority": "master",
    "description": "Inkontinenzprodukt in der Hand vor schwarzer Strumpfhose, Produktvolumen",
    "width": 1033,
    "height": 1720,
    "sha1": "b6243a72b343",
    "usage": "reference_only",
    "face_visibility": "not_primary_or_not_visible",
    "notes": "Original Nutzerreferenz. Für Prompting/CI/Asset-Matching verwenden; nicht ungeprüft öffentlich posten.",
    "path": "assets/references/outfits/tights_black/IMG_8896.jpeg"
  },
  {
    "id": "IMG_8895",
    "source_file": "IMG_8895.jpeg",
    "category": "diapers/product_in_hand",
    "priority": "master",
    "description": "Geöffnetes Inkontinenzprodukt mit Klett/Innenbereich als Produktreferenz",
    "width": 958,
    "height": 1692,
    "sha1": "be73cc64d5a7",
    "usage": "reference_only",
    "face_visibility": "not_primary_or_not_visible",
    "notes": "Original Nutzerreferenz. Für Prompting/CI/Asset-Matching verwenden; nicht ungeprüft öffentlich posten.",
    "path": "assets/references/diapers/product_in_hand/IMG_8895.jpeg"
  },
  {
    "id": "IMG_8895",
    "source_file": "IMG_8895.jpeg",
    "category": "diapers/details_closeup",
    "priority": "master",
    "description": "Geöffnetes Inkontinenzprodukt mit Klett/Innenbereich als Produktreferenz",
    "width": 958,
    "height": 1692,
    "sha1": "be73cc64d5a7",
    "usage": "reference_only",
    "face_visibility": "not_primary_or_not_visible",
    "notes": "Original Nutzerreferenz. Für Prompting/CI/Asset-Matching verwenden; nicht ungeprüft öffentlich posten.",
    "path": "assets/references/diapers/details_closeup/IMG_8895.jpeg"
  },
  {
    "id": "IMG_8895",
    "source_file": "IMG_8895.jpeg",
    "category": "outfits/tights_black",
    "priority": "master",
    "description": "Geöffnetes Inkontinenzprodukt mit Klett/Innenbereich als Produktreferenz",
    "width": 958,
    "height": 1692,
    "sha1": "be73cc64d5a7",
    "usage": "reference_only",
    "face_visibility": "not_primary_or_not_visible",
    "notes": "Original Nutzerreferenz. Für Prompting/CI/Asset-Matching verwenden; nicht ungeprüft öffentlich posten.",
    "path": "assets/references/outfits/tights_black/IMG_8895.jpeg"
  },
  {
    "id": "IMG_8894",
    "source_file": "IMG_8894.jpeg",
    "category": "diapers/waistband_visible",
    "priority": "master",
    "description": "Seitliche Silhouette: Windel sichtbar unter Kleidung/über Bund",
    "width": 550,
    "height": 1375,
    "sha1": "fda0b2c3f840",
    "usage": "reference_only",
    "face_visibility": "not_primary_or_not_visible",
    "notes": "Original Nutzerreferenz. Für Prompting/CI/Asset-Matching verwenden; nicht ungeprüft öffentlich posten.",
    "path": "assets/references/diapers/waistband_visible/IMG_8894.jpeg"
  },
  {
    "id": "IMG_8894",
    "source_file": "IMG_8894.jpeg",
    "category": "diapers/under_clothes_silhouette",
    "priority": "master",
    "description": "Seitliche Silhouette: Windel sichtbar unter Kleidung/über Bund",
    "width": 550,
    "height": 1375,
    "sha1": "fda0b2c3f840",
    "usage": "reference_only",
    "face_visibility": "not_primary_or_not_visible",
    "notes": "Original Nutzerreferenz. Für Prompting/CI/Asset-Matching verwenden; nicht ungeprüft öffentlich posten.",
    "path": "assets/references/diapers/under_clothes_silhouette/IMG_8894.jpeg"
  },
  {
    "id": "IMG_8894",
    "source_file": "IMG_8894.jpeg",
    "category": "outfits/tights_black",
    "priority": "master",
    "description": "Seitliche Silhouette: Windel sichtbar unter Kleidung/über Bund",
    "width": 550,
    "height": 1375,
    "sha1": "fda0b2c3f840",
    "usage": "reference_only",
    "face_visibility": "not_primary_or_not_visible",
    "notes": "Original Nutzerreferenz. Für Prompting/CI/Asset-Matching verwenden; nicht ungeprüft öffentlich posten.",
    "path": "assets/references/outfits/tights_black/IMG_8894.jpeg"
  },
  {
    "id": "IMG_8893",
    "source_file": "IMG_8893.jpeg",
    "category": "diapers/waistband_visible",
    "priority": "master",
    "description": "Windelbund sichtbar, seitliche Po-/Bundkontur als Alltagsreferenz",
    "width": 536,
    "height": 1001,
    "sha1": "596abf14c38c",
    "usage": "reference_only",
    "face_visibility": "not_primary_or_not_visible",
    "notes": "Original Nutzerreferenz. Für Prompting/CI/Asset-Matching verwenden; nicht ungeprüft öffentlich posten.",
    "path": "assets/references/diapers/waistband_visible/IMG_8893.jpeg"
  },
  {
    "id": "IMG_8893",
    "source_file": "IMG_8893.jpeg",
    "category": "diapers/under_clothes_silhouette",
    "priority": "master",
    "description": "Windelbund sichtbar, seitliche Po-/Bundkontur als Alltagsreferenz",
    "width": 536,
    "height": 1001,
    "sha1": "596abf14c38c",
    "usage": "reference_only",
    "face_visibility": "not_primary_or_not_visible",
    "notes": "Original Nutzerreferenz. Für Prompting/CI/Asset-Matching verwenden; nicht ungeprüft öffentlich posten.",
    "path": "assets/references/diapers/under_clothes_silhouette/IMG_8893.jpeg"
  },
  {
    "id": "IMG_8893",
    "source_file": "IMG_8893.jpeg",
    "category": "outfits/tights_black",
    "priority": "master",
    "description": "Windelbund sichtbar, seitliche Po-/Bundkontur als Alltagsreferenz",
    "width": 536,
    "height": 1001,
    "sha1": "596abf14c38c",
    "usage": "reference_only",
    "face_visibility": "not_primary_or_not_visible",
    "notes": "Original Nutzerreferenz. Für Prompting/CI/Asset-Matching verwenden; nicht ungeprüft öffentlich posten.",
    "path": "assets/references/outfits/tights_black/IMG_8893.jpeg"
  },
  {
    "id": "IMG_8891",
    "source_file": "IMG_8891.jpeg",
    "category": "diapers/waistband_visible",
    "priority": "approved",
    "description": "Nahaufnahme Windel/Strumpfhose/Bund, Klett-/Material-Kontext",
    "width": 1172,
    "height": 2043,
    "sha1": "9f04a357bcb7",
    "usage": "reference_only",
    "face_visibility": "not_primary_or_not_visible",
    "notes": "Original Nutzerreferenz. Für Prompting/CI/Asset-Matching verwenden; nicht ungeprüft öffentlich posten.",
    "path": "assets/references/diapers/waistband_visible/IMG_8891.jpeg"
  },
  {
    "id": "IMG_8891",
    "source_file": "IMG_8891.jpeg",
    "category": "diapers/details_closeup",
    "priority": "approved",
    "description": "Nahaufnahme Windel/Strumpfhose/Bund, Klett-/Material-Kontext",
    "width": 1172,
    "height": 2043,
    "sha1": "9f04a357bcb7",
    "usage": "reference_only",
    "face_visibility": "not_primary_or_not_visible",
    "notes": "Original Nutzerreferenz. Für Prompting/CI/Asset-Matching verwenden; nicht ungeprüft öffentlich posten.",
    "path": "assets/references/diapers/details_closeup/IMG_8891.jpeg"
  },
  {
    "id": "IMG_8891",
    "source_file": "IMG_8891.jpeg",
    "category": "outfits/tights_black",
    "priority": "approved",
    "description": "Nahaufnahme Windel/Strumpfhose/Bund, Klett-/Material-Kontext",
    "width": 1172,
    "height": 2043,
    "sha1": "9f04a357bcb7",
    "usage": "reference_only",
    "face_visibility": "not_primary_or_not_visible",
    "notes": "Original Nutzerreferenz. Für Prompting/CI/Asset-Matching verwenden; nicht ungeprüft öffentlich posten.",
    "path": "assets/references/outfits/tights_black/IMG_8891.jpeg"
  },
  {
    "id": "IMG_8889",
    "source_file": "IMG_8889.jpeg",
    "category": "diapers/waistband_visible",
    "priority": "approved",
    "description": "Nahaufnahme Windel am Bund, Hand/Strumpfhose, Detailreferenz",
    "width": 1155,
    "height": 2048,
    "sha1": "f43ad5902ec8",
    "usage": "reference_only",
    "face_visibility": "not_primary_or_not_visible",
    "notes": "Original Nutzerreferenz. Für Prompting/CI/Asset-Matching verwenden; nicht ungeprüft öffentlich posten.",
    "path": "assets/references/diapers/waistband_visible/IMG_8889.jpeg"
  },
  {
    "id": "IMG_8889",
    "source_file": "IMG_8889.jpeg",
    "category": "diapers/details_closeup",
    "priority": "approved",
    "description": "Nahaufnahme Windel am Bund, Hand/Strumpfhose, Detailreferenz",
    "width": 1155,
    "height": 2048,
    "sha1": "f43ad5902ec8",
    "usage": "reference_only",
    "face_visibility": "not_primary_or_not_visible",
    "notes": "Original Nutzerreferenz. Für Prompting/CI/Asset-Matching verwenden; nicht ungeprüft öffentlich posten.",
    "path": "assets/references/diapers/details_closeup/IMG_8889.jpeg"
  },
  {
    "id": "IMG_8889",
    "source_file": "IMG_8889.jpeg",
    "category": "outfits/tights_black",
    "priority": "approved",
    "description": "Nahaufnahme Windel am Bund, Hand/Strumpfhose, Detailreferenz",
    "width": 1155,
    "height": 2048,
    "sha1": "f43ad5902ec8",
    "usage": "reference_only",
    "face_visibility": "not_primary_or_not_visible",
    "notes": "Original Nutzerreferenz. Für Prompting/CI/Asset-Matching verwenden; nicht ungeprüft öffentlich posten.",
    "path": "assets/references/outfits/tights_black/IMG_8889.jpeg"
  },
  {
    "id": "a_multi_panel_instagram_style_carousel_layout_in_a",
    "source_file": "a_multi_panel_instagram_style_carousel_layout_in_a.png",
    "category": "rejected/generated_do_not_use",
    "priority": "rejected",
    "description": "Generierte Version, NICHT als Master verwenden; dient nur als Negativ-/Fehlerreferenz für Layout/Prompting",
    "width": 1024,
    "height": 1536,
    "sha1": "02fb7e02b121",
    "usage": "reference_only",
    "face_visibility": "not_primary_or_not_visible",
    "notes": "Original Nutzerreferenz. Für Prompting/CI/Asset-Matching verwenden; nicht ungeprüft öffentlich posten.",
    "path": "assets/references/rejected/generated_do_not_use/a_multi_panel_instagram_style_carousel_layout_in_a.png"
  },
  {
    "id": "a_lifestyle_street_transport_themed_photo_with_ove",
    "source_file": "a_lifestyle_street_transport_themed_photo_with_ove.png",
    "category": "rejected/generated_do_not_use",
    "priority": "rejected",
    "description": "Generierte Version, NICHT als Master verwenden; dient nur als Negativ-/Fehlerreferenz für Layout/Prompting",
    "width": 1122,
    "height": 1402,
    "sha1": "7625cc82e997",
    "usage": "reference_only",
    "face_visibility": "not_primary_or_not_visible",
    "notes": "Original Nutzerreferenz. Für Prompting/CI/Asset-Matching verwenden; nicht ungeprüft öffentlich posten.",
    "path": "assets/references/rejected/generated_do_not_use/a_lifestyle_street_transport_themed_photo_with_ove.png"
  },
  {
    "id": "a_collage_infographic_style_image_with_six_panels",
    "source_file": "a_collage_infographic_style_image_with_six_panels.png",
    "category": "rejected/generated_do_not_use",
    "priority": "rejected",
    "description": "Generierte Version, NICHT als Master verwenden; dient nur als Negativ-/Fehlerreferenz für Layout/Prompting",
    "width": 1023,
    "height": 1537,
    "sha1": "20f9cbecbb77",
    "usage": "reference_only",
    "face_visibility": "not_primary_or_not_visible",
    "notes": "Original Nutzerreferenz. Für Prompting/CI/Asset-Matching verwenden; nicht ungeprüft öffentlich posten.",
    "path": "assets/references/rejected/generated_do_not_use/a_collage_infographic_style_image_with_six_panels.png"
  }
]